jamcalci/__init__.py
jamcalci-0.0.2.dist-info/LICENCE.txt
jamcalci-0.0.2.dist-info/METADATA
jamcalci-0.0.2.dist-info/WHEEL
jamcalci-0.0.2.dist-info/top_level.txt
jamcalci-0.0.2.dist-info/RECORD
