Metadata-Version: 2.1
Name: jamcalci
Version: 0.0.2
Summary: A basic calculator
Home-page: https://github.com/ONKARJAMMA/Jamcalci
Author: Onkar Jamma
Author-email: onkarjamma1@gmail.com
License: MIT
Keywords: calculator
Classifier: Development Status :: 5 - Production/Stable
Classifier: Intended Audience :: Education
Classifier: Operating System :: Microsoft :: Windows :: Windows 11
Classifier: License :: OSI Approved :: MIT License
Classifier: Programming Language :: Python :: 3
Requires-Python: >=3.6
License-File: LICENCE.txt
